alessandro_c_mod1_atsiskaitymas/__init__.py
alessandro_c_mod1_atsiskaitymas/web_crawler.py
tests/__init__.py
tests/test_web_crawler.py
alessandro_c_mod1_atsiskaitymas-0.1.0.dist-info/METADATA
alessandro_c_mod1_atsiskaitymas-0.1.0.dist-info/WHEEL
alessandro_c_mod1_atsiskaitymas-0.1.0.dist-info/top_level.txt
alessandro_c_mod1_atsiskaitymas-0.1.0.dist-info/RECORD
