Metadata-Version: 2.1
Name: alessandro_c_mod1_atsiskaitymas
Version: 0.1.0
Summary: Web crawler
Home-page: https://github.com/ales-sandrito/alessandro-c-mod1-atsiskaitymas
Author: Alessandro Caliva
Author-email: calivaalessandro@gmail.com
Classifier: Programming Language :: Python :: 3
Requires-Python: >=3.10
Requires-Dist: certifi==2024.8.30
Requires-Dist: charset-normalizer==3.4.0
Requires-Dist: idna==3.10
Requires-Dist: lxml==5.3.0
Requires-Dist: pip==23.2.1
Requires-Dist: requests==2.32.3
Requires-Dist: setuptools==75.5.0
Requires-Dist: soupsieve==2.6
Requires-Dist: urllib3==2.2.3
Requires-Dist: wheel==0.45.1
Requires-Dist: twine==5.1.1
